[{"product_id": "5119790-EA-000PNS", "product_name": "Slavica Bakery Crunchy Sultana Biscuits", "price_mode": "ea", "price_item": "2.49", "url": "/product/5119790_ea_000pns?name=crunchy-sultana-biscuits", "cat1": "Fresh Foods & Bakery", "cat2": "Bakery", "cat_url": "/category/fresh-foods-and-bakery/bakery", "store_name": "PAK'nSAVE Lower Hutt"}, {"product_id": "5022350-EA-000PNS", "product_name": "La Famiglia Garlic Bread", "price_mode": "ea", "price_item": "4.79", "url": "/product/5022350_ea_000pns?name=garlic-bread", "cat1": "Fresh Foods & Bakery", "cat2": "Bakery", "cat_url": "/category/fresh-foods-and-bakery/bakery", "store_name": "PAK'nSAVE Lower Hutt"}, {"product_id": "5041433-EA-000PNS", "product_name": "Bakery Garlic Bread", "price_mode": "ea", "price_item": "3.99", "url": "/product/5041433_ea_000pns?name=garlic-bread", "cat1": "Fresh Foods & Bakery", "cat2": "Bakery", "cat_url": "/category/fresh-foods-and-bakery/bakery", "store_name": "PAK'nSAVE Lower Hutt"}, {"product_id": "5221912-EA-000PNS", "product_name": "Turkish Bread Garlic Naan Bread", "price_mode": "ea", "price_item": "3.79", "url": "/product/5221912_ea_000pns?name=garlic-naan-bread", "cat1": "Fresh Foods & Bakery", "cat2": "Bakery", "cat_url": "/category/fresh-foods-and-bakery/bakery", "store_name": "PAK'nSAVE Lower Hutt"}, {"product_id": "5084035-EA-000PNS", "product_name": "Jon-Jon Ginger Kisses", "price_mode": "ea", "price_item": "2.99", "url": "/product/5084035_ea_000pns?name=ginger-kisses", "cat1": "Fresh Foods & Bakery", "cat2": "Bakery", "cat_url": "/category/fresh-foods-and-bakery/bakery", "store_name": "PAK'nSAVE Lower Hutt"}, {"product_id": "5104696-EA-000PNS", "product_name": "Baker Boys Afghan Biscuits", "price_mode": "ea", "price_item": "7.29", "url": "/product/5104696_ea_000pns?name=afghan-biscuits", "cat1": "Fresh Foods & Bakery", "cat2": "Bakery", "cat_url": "/category/fresh-foods-and-bakery/bakery", "store_name": "PAK'nSAVE Lower Hutt"}, {"product_id": "5031763-EA-000PNS", "product_name": "Freya's Spinach & Garden Herb Wraps", "price_mode": "ea", "price_item": "4.49", "url": "/product/5031763_ea_000pns?name=spinach-%26-garden-herb-wraps", "cat1": "Fresh Foods & Bakery", "cat2": "Bakery", "cat_url": "/category/fresh-foods-and-bakery/bakery", "store_name": "PAK'nSAVE Lower Hutt"}, {"product_id": "5125200-EA-000PNS", "product_name": "Marcel's Mini Hotcakes", "price_mode": "ea", "price_item": "3.24", "url": "/product/5125200_ea_000pns?name=mini-hotcakes", "cat1": "Fresh Foods & Bakery", "cat2": "Bakery", "cat_url": "/category/fresh-foods-and-bakery/bakery", "store_name": "PAK'nSAVE Lower Hutt"}, {"product_id": "5228482-EA-000PNS", "product_name": "Abe's The Everything Bagels", "price_mode": "ea", "price_item": "4.19", "url": "/product/5228482_ea_000pns?name=the-everything-bagels", "cat1": "Fresh Foods & Bakery", "cat2": "Bakery", "cat_url": "/category/fresh-foods-and-bakery/bakery", "store_name": "PAK'nSAVE Lower Hutt"}, {"product_id": "5017673-EA-000PNS", "product_name": "Vogel's Gluten Free White Bread", "price_mode": "ea", "price_item": "7.49", "url": "/product/5017673_ea_000pns?name=gluten-free-white-bread", "cat1": "Fresh Foods & Bakery", "cat2": "Bakery", "cat_url": "/category/fresh-foods-and-bakery/bakery", "store_name": "PAK'nSAVE Lower Hutt"}, {"product_id": "5115388-EA-000PNS", "product_name": "Bakery Turkish Bread", "price_mode": "ea", "price_item": "1.99", "url": "/product/5115388_ea_000pns?name=turkish-bread", "cat1": "Fresh Foods & Bakery", "cat2": "Bakery", "cat_url": "/category/fresh-foods-and-bakery/bakery", "store_name": "PAK'nSAVE Lower Hutt"}, {"product_id": "5103226-EA-000PNS", "product_name": "Bakery Chelsea Bun", "price_mode": "ea", "price_item": "1.50", "url": "/product/5103226_ea_000pns?name=chelsea-bun", "cat1": "Fresh Foods & Bakery", "cat2": "Bakery", "cat_url": "/category/fresh-foods-and-bakery/bakery", "store_name": "PAK'nSAVE Lower Hutt"}, {"product_id": "5245415-EA-000PNS", "product_name": "Tip Top Supersoft Hotdog Rolls", "price_mode": "ea", "price_item": "2.99", "url": "/product/5245415_ea_000pns?name=supersoft-hotdog-rolls", "cat1": "Fresh Foods & Bakery", "cat2": "Bakery", "cat_url": "/category/fresh-foods-and-bakery/bakery", "store_name": "PAK'nSAVE Lower Hutt"}, {"product_id": "5106367-EA-000PNS", "product_name": "Bakery Mock Cream Buns", "price_mode": "ea", "price_item": "4.49", "url": "/product/5106367_ea_000pns?name=mock-cream-buns", "cat1": "Fresh Foods & Bakery", "cat2": "Bakery", "cat_url": "/category/fresh-foods-and-bakery/bakery", "store_name": "PAK'nSAVE Lower Hutt"}, {"product_id": "5026388-EA-000PNS", "product_name": "Turkish Bread Garlic Pizza Bread", "price_mode": "ea", "price_item": "3.29", "url": "/product/5026388_ea_000pns?name=garlic-pizza-bread", "cat1": "Fresh Foods & Bakery", "cat2": "Bakery", "cat_url": "/category/fresh-foods-and-bakery/bakery", "store_name": "PAK'nSAVE Lower Hutt"}, {"product_id": "5041762-EA-000PNS", "product_name": "Bakery Texas Muffins", "price_mode": "ea", "price_item": "4.99", "url": "/product/5041762_ea_000pns?name=texas-muffins", "cat1": "Fresh Foods & Bakery", "cat2": "Bakery", "cat_url": "/category/fresh-foods-and-bakery/bakery", "store_name": "PAK'nSAVE Lower Hutt"}, {"product_id": "5112849-EA-000PNS", "product_name": "Bakery Raspberry Finger Buns", "price_mode": "ea", "price_item": "3.99", "url": "/product/5112849_ea_000pns?name=raspberry-finger-buns", "cat1": "Fresh Foods & Bakery", "cat2": "Bakery", "cat_url": "/category/fresh-foods-and-bakery/bakery", "store_name": "PAK'nSAVE Lower Hutt"}, {"product_id": "5219023-EA-000PNS", "product_name": "Farrah's Caramelised Onion Wraps", "price_mode": "ea", "price_item": "5.19", "url": "/product/5219023_ea_000pns?name=caramelised-onion-wraps", "cat1": "Fresh Foods & Bakery", "cat2": "Bakery", "cat_url": "/category/fresh-foods-and-bakery/bakery", "store_name": "PAK'nSAVE Lower Hutt"}, {"product_id": "5021310-EA-000PNS", "product_name": "Farrah's Kids White Snack Wraps", "price_mode": "ea", "price_item": "5.19", "url": "/product/5021310_ea_000pns?name=kids-white-snack-wraps", "cat1": "Fresh Foods & Bakery", "cat2": "Bakery", "cat_url": "/category/fresh-foods-and-bakery/bakery", "store_name": "PAK'nSAVE Lower Hutt"}, {"product_id": "5019271-EA-000PNS", "product_name": "Artisan Bakehouse Garlic Bread", "price_mode": "ea", "price_item": "4.49", "url": "/product/5019271_ea_000pns?name=garlic-bread", "cat1": "Fresh Foods & Bakery", "cat2": "Bakery", "cat_url": "/category/fresh-foods-and-bakery/bakery", "store_name": "PAK'nSAVE Lower Hutt"}]