[{"product_id": "5259034-EA-000PNS", "product_name": "AMS Proactive Health Minichunks Adult Chicken Dry Dog Food", "price_mode": "a", "price_item": "15.99", "url": "/product/5259034_ea_000pns?name=proactive-health-minichunks-adult-chicken-dry-dog-food", "cat1": "Pets", "cat2": "Pet Supplies", "cat_url": "/category/pets/pet-supplies", "store_name": "PAK'nSAVE Mangere"}, {"product_id": "5259034-EA-000PNS", "product_name": "AMS Proactive Health Minichunks Adult Chicken Dry Dog Food", "price_mode": "a", "price_item": "15.99", "url": "/product/5259034_ea_000pns?name=proactive-health-minichunks-adult-chicken-dry-dog-food", "cat1": "Pets", "cat2": "Pet Supplies", "cat_url": "/category/pets/pet-supplies", "store_name": "PAK'nSAVE Mangere"}, {"product_id": "5259034-EA-000PNS", "product_name": "AMS Proactive Health Minichunks Adult Chicken Dry Dog Food", "price_mode": "a", "price_item": "15.99", "url": "/product/5259034_ea_000pns?name=proactive-health-minichunks-adult-chicken-dry-dog-food", "cat1": "Pets", "cat2": "Pet Supplies", "cat_url": "/category/pets/pet-supplies", "store_name": "PAK'nSAVE Mangere"}, {"product_id": "5259034-EA-000PNS", "product_name": "AMS Proactive Health Minichunks Adult Chicken Dry Dog Food", "price_mode": "a", "price_item": "15.99", "url": "/product/5259034_ea_000pns?name=proactive-health-minichunks-adult-chicken-dry-dog-food", "cat1": "Pets", "cat2": "Pet Supplies", "cat_url": "/category/pets/pet-supplies", "store_name": "PAK'nSAVE Mangere"}, {"product_id": "5259034-EA-000PNS", "product_name": "AMS Proactive Health Minichunks Adult Chicken Dry Dog Food", "price_mode": "a", "price_item": "15.99", "url": "/product/5259034_ea_000pns?name=proactive-health-minichunks-adult-chicken-dry-dog-food", "cat1": "Pets", "cat2": "Pet Supplies", "cat_url": "/category/pets/pet-supplies", "store_name": "PAK'nSAVE Mangere"}, {"product_id": "5259034-EA-000PNS", "product_name": "AMS Proactive Health Minichunks Adult Chicken Dry Dog Food", "price_mode": "a", "price_item": "15.99", "url": "/product/5259034_ea_000pns?name=proactive-health-minichunks-adult-chicken-dry-dog-food", "cat1": "Pets", "cat2": "Pet Supplies", "cat_url": "/category/pets/pet-supplies", "store_name": "PAK'nSAVE Mangere"}, {"product_id": "5259034-EA-000PNS", "product_name": "AMS Proactive Health Minichunks Adult Chicken Dry Dog Food", "price_mode": "a", "price_item": "15.99", "url": "/product/5259034_ea_000pns?name=proactive-health-minichunks-adult-chicken-dry-dog-food", "cat1": "Pets", "cat2": "Pet Supplies", "cat_url": "/category/pets/pet-supplies", "store_name": "PAK'nSAVE Mangere"}, {"product_id": "5259034-EA-000PNS", "product_name": "AMS Proactive Health Minichunks Adult Chicken Dry Dog Food", "price_mode": "a", "price_item": "15.99", "url": "/product/5259034_ea_000pns?name=proactive-health-minichunks-adult-chicken-dry-dog-food", "cat1": "Pets", "cat2": "Pet Supplies", "cat_url": "/category/pets/pet-supplies", "store_name": "PAK'nSAVE Mangere"}, {"product_id": "5259034-EA-000PNS", "product_name": "AMS Proactive Health Minichunks Adult Chicken Dry Dog Food", "price_mode": "a", "price_item": "15.99", "url": "/product/5259034_ea_000pns?name=proactive-health-minichunks-adult-chicken-dry-dog-food", "cat1": "Pets", "cat2": "Pet Supplies", "cat_url": "/category/pets/pet-supplies", "store_name": "PAK'nSAVE Mangere"}, {"product_id": "5259034-EA-000PNS", "product_name": "AMS Proactive Health Minichunks Adult Chicken Dry Dog Food", "price_mode": "a", "price_item": "15.99", "url": "/product/5259034_ea_000pns?name=proactive-health-minichunks-adult-chicken-dry-dog-food", "cat1": "Pets", "cat2": "Pet Supplies", "cat_url": "/category/pets/pet-supplies", "store_name": "PAK'nSAVE Mangere"}, {"product_id": "5259034-EA-000PNS", "product_name": "AMS Proactive Health Minichunks Adult Chicken Dry Dog Food", "price_mode": "a", "price_item": "15.99", "url": "/product/5259034_ea_000pns?name=proactive-health-minichunks-adult-chicken-dry-dog-food", "cat1": "Pets", "cat2": "Pet Supplies", "cat_url": "/category/pets/pet-supplies", "store_name": "PAK'nSAVE Mangere"}, {"product_id": "5259034-EA-000PNS", "product_name": "AMS Proactive Health Minichunks Adult Chicken Dry Dog Food", "price_mode": "a", "price_item": "15.99", "url": "/product/5259034_ea_000pns?name=proactive-health-minichunks-adult-chicken-dry-dog-food", "cat1": "Pets", "cat2": "Pet Supplies", "cat_url": "/category/pets/pet-supplies", "store_name": "PAK'nSAVE Mangere"}, {"product_id": "5259034-EA-000PNS", "product_name": "AMS Proactive Health Minichunks Adult Chicken Dry Dog Food", "price_mode": "a", "price_item": "15.99", "url": "/product/5259034_ea_000pns?name=proactive-health-minichunks-adult-chicken-dry-dog-food", "cat1": "Pets", "cat2": "Pet Supplies", "cat_url": "/category/pets/pet-supplies", "store_name": "PAK'nSAVE Mangere"}, {"product_id": "5259034-EA-000PNS", "product_name": "AMS Proactive Health Minichunks Adult Chicken Dry Dog Food", "price_mode": "a", "price_item": "15.99", "url": "/product/5259034_ea_000pns?name=proactive-health-minichunks-adult-chicken-dry-dog-food", "cat1": "Pets", "cat2": "Pet Supplies", "cat_url": "/category/pets/pet-supplies", "store_name": "PAK'nSAVE Mangere"}, {"product_id": "5259034-EA-000PNS", "product_name": "AMS Proactive Health Minichunks Adult Chicken Dry Dog Food", "price_mode": "a", "price_item": "15.99", "url": "/product/5259034_ea_000pns?name=proactive-health-minichunks-adult-chicken-dry-dog-food", "cat1": "Pets", "cat2": "Pet Supplies", "cat_url": "/category/pets/pet-supplies", "store_name": "PAK'nSAVE Mangere"}, {"product_id": "5259034-EA-000PNS", "product_name": "AMS Proactive Health Minichunks Adult Chicken Dry Dog Food", "price_mode": "a", "price_item": "15.99", "url": "/product/5259034_ea_000pns?name=proactive-health-minichunks-adult-chicken-dry-dog-food", "cat1": "Pets", "cat2": "Pet Supplies", "cat_url": "/category/pets/pet-supplies", "store_name": "PAK'nSAVE Mangere"}, {"product_id": "5259034-EA-000PNS", "product_name": "AMS Proactive Health Minichunks Adult Chicken Dry Dog Food", "price_mode": "a", "price_item": "15.99", "url": "/product/5259034_ea_000pns?name=proactive-health-minichunks-adult-chicken-dry-dog-food", "cat1": "Pets", "cat2": "Pet Supplies", "cat_url": "/category/pets/pet-supplies", "store_name": "PAK'nSAVE Mangere"}, {"product_id": "5259034-EA-000PNS", "product_name": "AMS Proactive Health Minichunks Adult Chicken Dry Dog Food", "price_mode": "a", "price_item": "15.99", "url": "/product/5259034_ea_000pns?name=proactive-health-minichunks-adult-chicken-dry-dog-food", "cat1": "Pets", "cat2": "Pet Supplies", "cat_url": "/category/pets/pet-supplies", "store_name": "PAK'nSAVE Mangere"}, {"product_id": "5259034-EA-000PNS", "product_name": "AMS Proactive Health Minichunks Adult Chicken Dry Dog Food", "price_mode": "a", "price_item": "15.99", "url": "/product/5259034_ea_000pns?name=proactive-health-minichunks-adult-chicken-dry-dog-food", "cat1": "Pets", "cat2": "Pet Supplies", "cat_url": "/category/pets/pet-supplies", "store_name": "PAK'nSAVE Mangere"}, {"product_id": "5259034-EA-000PNS", "product_name": "AMS Proactive Health Minichunks Adult Chicken Dry Dog Food", "price_mode": "a", "price_item": "15.99", "url": "/product/5259034_ea_000pns?name=proactive-health-minichunks-adult-chicken-dry-dog-food", "cat1": "Pets", "cat2": "Pet Supplies", "cat_url": "/category/pets/pet-supplies", "store_name": "PAK'nSAVE Mangere"}]