[{"product_id": "5012083-EA-000PNS", "product_name": "Sodastream Diet Cola Flavoured Drink Concentrate", "price_mode": "ea", "price_item": "7.99", "url": "/product/5012083_ea_000pns?name=diet-cola-flavoured-drink-concentrate", "cat1": "Drinks", "cat2": "Cold Drinks", "cat_url": "/category/drinks/cold-drinks", "store_name": "PAK'nSAVE Porirua"}, {"product_id": "5266706-EA-000PNS", "product_name": "Coca-Cola Orange No Sugar Soft Drink Cans", "price_mode": "ea", "price_item": "5.99", "url": "/product/5266706_ea_000pns?name=orange-no-sugar-soft-drink-cans", "cat1": "Drinks", "cat2": "Cold Drinks", "cat_url": "/category/drinks/cold-drinks", "store_name": "PAK'nSAVE Porirua"}, {"product_id": "5015717-EA-000PNS", "product_name": "Pump Spring Water Mini", "price_mode": "ea", "price_item": "6.99", "url": "/product/5015717_ea_000pns?name=spring-water-mini", "cat1": "Drinks", "cat2": "Cold Drinks", "cat_url": "/category/drinks/cold-drinks", "store_name": "PAK'nSAVE Porirua"}, {"product_id": "5002460-EA-000PNS", "product_name": "Ribena Blackcurrant Fruit Drink", "price_mode": "ea", "price_item": "2.49", "url": "/product/5002460_ea_000pns?name=blackcurrant-fruit-drink", "cat1": "Drinks", "cat2": "Cold Drinks", "cat_url": "/category/drinks/cold-drinks", "store_name": "PAK'nSAVE Porirua"}, {"product_id": "5247977-EA-000PNS", "product_name": "V8 Power Blend Rainbow Burst Juice", "price_mode": "ea", "price_item": "4.79", "url": "/product/5247977_ea_000pns?name=power-blend-rainbow-burst-juice", "cat1": "Drinks", "cat2": "Cold Drinks", "cat_url": "/category/drinks/cold-drinks", "store_name": "PAK'nSAVE Porirua"}, {"product_id": "5254350-EA-000PNS", "product_name": "V Sugar Free Berry Twist Guarana Energy Drink", "price_mode": "ea", "price_item": "2.49", "url": "/product/5254350_ea_000pns?name=sugar-free-berry-twist-guarana-energy-drink", "cat1": "Drinks", "cat2": "Cold Drinks", "cat_url": "/category/drinks/cold-drinks", "store_name": "PAK'nSAVE Porirua"}, {"product_id": "5264578-EA-000PNS", "product_name": "McCoy Balance Apple Pear Rhubarb & Mint Premium Juice", "price_mode": "ea", "price_item": "3.49", "url": "/product/5264578_ea_000pns?name=balance-apple-pear-rhubarb-%26-mint-premium-juice", "cat1": "Drinks", "cat2": "Cold Drinks", "cat_url": "/category/drinks/cold-drinks", "store_name": "PAK'nSAVE Porirua"}, {"product_id": "5025512-EA-000PNS", "product_name": "Sodastream Orange Flavoured Drink Concentrate", "price_mode": "ea", "price_item": "7.99", "url": "/product/5025512_ea_000pns?name=orange-flavoured-drink-concentrate", "cat1": "Drinks", "cat2": "Cold Drinks", "cat_url": "/category/drinks/cold-drinks", "store_name": "PAK'nSAVE Porirua"}, {"product_id": "5013050-EA-000PNS", "product_name": "Sodastream Sugar Free Lemonade Flavoured Drink Concentrate", "price_mode": "ea", "price_item": "7.99", "url": "/product/5013050_ea_000pns?name=sugar-free-lemonade-flavoured-drink-concentrate", "cat1": "Drinks", "cat2": "Cold Drinks", "cat_url": "/category/drinks/cold-drinks", "store_name": "PAK'nSAVE Porirua"}, {"product_id": "5002891-EA-000PNS", "product_name": "McCoy Orange Juice", "price_mode": "ea", "price_item": "3.29", "url": "/product/5002891_ea_000pns?name=orange-juice", "cat1": "Drinks", "cat2": "Cold Drinks", "cat_url": "/category/drinks/cold-drinks", "store_name": "PAK'nSAVE Porirua"}, {"product_id": "5087369-EA-000PNS", "product_name": "TCC Pure Coconut Water", "price_mode": "ea", "price_item": "2.29", "url": "/product/5087369_ea_000pns?name=pure-coconut-water", "cat1": "Drinks", "cat2": "Cold Drinks", "cat_url": "/category/drinks/cold-drinks", "store_name": "PAK'nSAVE Porirua"}, {"product_id": "5211883-EA-000PNS", "product_name": "Ocean Spray Cran Blueberry Fruit Drink", "price_mode": "ea", "price_item": "4.99", "url": "/product/5211883_ea_000pns?name=cran-blueberry-fruit-drink", "cat1": "Drinks", "cat2": "Cold Drinks", "cat_url": "/category/drinks/cold-drinks", "store_name": "PAK'nSAVE Porirua"}, {"product_id": "5264590-EA-000PNS", "product_name": "V8 Super Orange Fruit & Veg Juice", "price_mode": "ea", "price_item": "4.29", "url": "/product/5264590_ea_000pns?name=super-orange-fruit-%26-veg-juice", "cat1": "Drinks", "cat2": "Cold Drinks", "cat_url": "/category/drinks/cold-drinks", "store_name": "PAK'nSAVE Porirua"}, {"product_id": "5086900-EA-000PNS", "product_name": "Sodastream Diet Ginger Beer Flavoured Drink Concentrate", "price_mode": "ea", "price_item": "7.99", "url": "/product/5086900_ea_000pns?name=diet-ginger-beer-flavoured-drink-concentrate", "cat1": "Drinks", "cat2": "Cold Drinks", "cat_url": "/category/drinks/cold-drinks", "store_name": "PAK'nSAVE Porirua"}, {"product_id": "5264591-EA-000PNS", "product_name": "V8 Healthy Apple Fruit & Veg Juice", "price_mode": "ea", "price_item": "4.29", "url": "/product/5264591_ea_000pns?name=healthy-apple-fruit-%26-veg-juice", "cat1": "Drinks", "cat2": "Cold Drinks", "cat_url": "/category/drinks/cold-drinks", "store_name": "PAK'nSAVE Porirua"}, {"product_id": "5012085-EA-000PNS", "product_name": "Sodastream Summer Lemon Flavoured Drink Concentrate", "price_mode": "ea", "price_item": "7.99", "url": "/product/5012085_ea_000pns?name=summer-lemon-flavoured-drink-concentrate", "cat1": "Drinks", "cat2": "Cold Drinks", "cat_url": "/category/drinks/cold-drinks", "store_name": "PAK'nSAVE Porirua"}, {"product_id": "5100273-EA-000PNS", "product_name": "Sodastream Sugar Free Cranberry Raspberry Flavoured Drink Concentrate", "price_mode": "ea", "price_item": "7.99", "url": "/product/5100273_ea_000pns?name=sugar-free-cranberry-raspberry-flavoured-drink-concentrate", "cat1": "Drinks", "cat2": "Cold Drinks", "cat_url": "/category/drinks/cold-drinks", "store_name": "PAK'nSAVE Porirua"}, {"product_id": "5269984-EA-000PNS", "product_name": "Nestle Milo Xtra Energy Drink", "price_mode": "ea", "price_item": "5.99", "url": "/product/5269984_ea_000pns?name=milo-xtra-energy-drink", "cat1": "Drinks", "cat2": "Cold Drinks", "cat_url": "/category/drinks/cold-drinks", "store_name": "PAK'nSAVE Porirua"}, {"product_id": "5010155-EA-000PNS", "product_name": "Fresh Up Harvest Red Apple Juice", "price_mode": "ea", "price_item": "1.99", "url": "/product/5010155_ea_000pns?name=harvest-red-apple-juice", "cat1": "Drinks", "cat2": "Cold Drinks", "cat_url": "/category/drinks/cold-drinks", "store_name": "PAK'nSAVE Porirua"}, {"product_id": "5016446-EA-000PNS", "product_name": "Shott Passionfruit Real Fruit Syrup", "price_mode": "ea", "price_item": "8.79", "url": "/product/5016446_ea_000pns?name=passionfruit-real-fruit-syrup", "cat1": "Drinks", "cat2": "Cold Drinks", "cat_url": "/category/drinks/cold-drinks", "store_name": "PAK'nSAVE Porirua"}]