[{"product_id": "5090969-EA-000PNS", "product_name": "Fever-Tree Premium Indian Tonic Water", "price_mode": "ea", "price_item": "3.79", "url": "/product/5090969_ea_000pns?name=premium-indian-tonic-water", "cat1": "Drinks", "cat2": "Cold Drinks", "cat_url": "/category/drinks/cold-drinks", "store_name": "PAK'nSAVE Clarence St"}, {"product_id": "5241771-EA-000PNS", "product_name": "Amplify Raspberry Lime Organic Kombucha", "price_mode": "ea", "price_item": "2.29", "url": "/product/5241771_ea_000pns?name=raspberry-lime-organic-kombucha", "cat1": "Drinks", "cat2": "Cold Drinks", "cat_url": "/category/drinks/cold-drinks", "store_name": "PAK'nSAVE Clarence St"}, {"product_id": "5233019-EA-000PNS", "product_name": "The Apple Press Braeburn Cold Pressed Apple Juice", "price_mode": "ea", "price_item": "3.49", "url": "/product/5233019_ea_000pns?name=braeburn-cold-pressed-apple-juice", "cat1": "Drinks", "cat2": "Cold Drinks", "cat_url": "/category/drinks/cold-drinks", "store_name": "PAK'nSAVE Clarence St"}, {"product_id": "5107264-EA-000PNS", "product_name": "Monster Energy Drink", "price_mode": "ea", "price_item": "11.19", "url": "/product/5107264_ea_000pns?name=energy-drink", "cat1": "Drinks", "cat2": "Cold Drinks", "cat_url": "/category/drinks/cold-drinks", "store_name": "PAK'nSAVE Clarence St"}, {"product_id": "5252401-EA-000PNS", "product_name": "Amplify Apple Blackcurrant Organic Kombucha", "price_mode": "ea", "price_item": "5.49", "url": "/product/5252401_ea_000pns?name=apple-blackcurrant-organic-kombucha", "cat1": "Drinks", "cat2": "Cold Drinks", "cat_url": "/category/drinks/cold-drinks", "store_name": "PAK'nSAVE Clarence St"}, {"product_id": "5262893-EA-000PNS", "product_name": "Lo Bros Ginger & Lemon Kombucha", "price_mode": "ea", "price_item": "5.99", "url": "/product/5262893_ea_000pns?name=ginger-%26-lemon-kombucha", "cat1": "Drinks", "cat2": "Cold Drinks", "cat_url": "/category/drinks/cold-drinks", "store_name": "PAK'nSAVE Clarence St"}, {"product_id": "5252558-EA-000PNS", "product_name": "Ocean Spray Pink Cranberry Juice", "price_mode": "ea", "price_item": "4.99", "url": "/product/5252558_ea_000pns?name=pink-cranberry-juice", "cat1": "Drinks", "cat2": "Cold Drinks", "cat_url": "/category/drinks/cold-drinks", "store_name": "PAK'nSAVE Clarence St"}, {"product_id": "5007771-EA-000PNS", "product_name": "Bundaberg Lemon Lime & Bitters", "price_mode": "ea", "price_item": "3.29", "url": "/product/5007771_ea_000pns?name=lemon-lime-%26-bitters", "cat1": "Drinks", "cat2": "Cold Drinks", "cat_url": "/category/drinks/cold-drinks", "store_name": "PAK'nSAVE Clarence St"}, {"product_id": "5262742-EA-000PNS", "product_name": "Lipton Lightly Sweetened Peach & Nectarine Flavour Ice Tea", "price_mode": "ea", "price_item": "3.79", "url": "/product/5262742_ea_000pns?name=lightly-sweetened-peach-%26-nectarine-flavour-ice-tea", "cat1": "Drinks", "cat2": "Cold Drinks", "cat_url": "/category/drinks/cold-drinks", "store_name": "PAK'nSAVE Clarence St"}, {"product_id": "5034698-EA-000PNS", "product_name": "Longest Drink Lime Milkshake Syrup", "price_mode": "ea", "price_item": "4.49", "url": "/product/5034698_ea_000pns?name=lime-milkshake-syrup", "cat1": "Drinks", "cat2": "Cold Drinks", "cat_url": "/category/drinks/cold-drinks", "store_name": "PAK'nSAVE Clarence St"}, {"product_id": "5262897-EA-000PNS", "product_name": "Lo Bros Lemon Lime & Bitter Kombucha", "price_mode": "ea", "price_item": "5.99", "url": "/product/5262897_ea_000pns?name=lemon-lime-%26-bitter-kombucha", "cat1": "Drinks", "cat2": "Cold Drinks", "cat_url": "/category/drinks/cold-drinks", "store_name": "PAK'nSAVE Clarence St"}, {"product_id": "5034697-EA-000PNS", "product_name": "Longest Drink Strawberry Milkshake Syrup", "price_mode": "ea", "price_item": "4.49", "url": "/product/5034697_ea_000pns?name=strawberry-milkshake-syrup", "cat1": "Drinks", "cat2": "Cold Drinks", "cat_url": "/category/drinks/cold-drinks", "store_name": "PAK'nSAVE Clarence St"}, {"product_id": "5262898-EA-000PNS", "product_name": "Lo Bros Ginger Beer Kombucha", "price_mode": "ea", "price_item": "5.99", "url": "/product/5262898_ea_000pns?name=ginger-beer-kombucha", "cat1": "Drinks", "cat2": "Cold Drinks", "cat_url": "/category/drinks/cold-drinks", "store_name": "PAK'nSAVE Clarence St"}, {"product_id": "5241342-EA-000PNS", "product_name": "The Apple Press Valenica Pulpy Orange & Cold Pressed Braeburn Apple Juice", "price_mode": "ea", "price_item": "4.99", "url": "/product/5241342_ea_000pns?name=valenica-pulpy-orange-%26-cold-pressed-braeburn-apple-juice", "cat1": "Drinks", "cat2": "Cold Drinks", "cat_url": "/category/drinks/cold-drinks", "store_name": "PAK'nSAVE Clarence St"}, {"product_id": "5245560-EA-000PNS", "product_name": "Fever-Tree Mediterranean Tonic Water", "price_mode": "ea", "price_item": "3.79", "url": "/product/5245560_ea_000pns?name=mediterranean-tonic-water", "cat1": "Drinks", "cat2": "Cold Drinks", "cat_url": "/category/drinks/cold-drinks", "store_name": "PAK'nSAVE Clarence St"}, {"product_id": "5019451-EA-000PNS", "product_name": "Coca-Cola Soft Drink", "price_mode": "ea", "price_item": "3.00", "url": "/product/5019451_ea_000pns?name=soft-drink", "cat1": "Drinks", "cat2": "Cold Drinks", "cat_url": "/category/drinks/cold-drinks", "store_name": "PAK'nSAVE Clarence St"}, {"product_id": "5203631-EA-000PNS", "product_name": "Daily Organics Summer Kombucha", "price_mode": "ea", "price_item": "14.29", "url": "/product/5203631_ea_000pns?name=summer-kombucha", "cat1": "Drinks", "cat2": "Cold Drinks", "cat_url": "/category/drinks/cold-drinks", "store_name": "PAK'nSAVE Clarence St"}, {"product_id": "5266704-EA-000PNS", "product_name": "Coca-Cola Orange No Sugar Soft Drink", "price_mode": "ea", "price_item": "3.79", "url": "/product/5266704_ea_000pns?name=orange-no-sugar-soft-drink", "cat1": "Drinks", "cat2": "Cold Drinks", "cat_url": "/category/drinks/cold-drinks", "store_name": "PAK'nSAVE Clarence St"}, {"product_id": "5237392-EA-000PNS", "product_name": "Live Plus Ascend Energy Drink", "price_mode": "ea", "price_item": "5.00", "url": "/product/5237392_ea_000pns?name=ascend-energy-drink", "cat1": "Drinks", "cat2": "Cold Drinks", "cat_url": "/category/drinks/cold-drinks", "store_name": "PAK'nSAVE Clarence St"}, {"product_id": "5034696-EA-000PNS", "product_name": "Longest Drink Banana Milkshake Syrup", "price_mode": "ea", "price_item": "4.49", "url": "/product/5034696_ea_000pns?name=banana-milkshake-syrup", "cat1": "Drinks", "cat2": "Cold Drinks", "cat_url": "/category/drinks/cold-drinks", "store_name": "PAK'nSAVE Clarence St"}]