[{"product_id": "5233769-EA-000PNS", "product_name": "Glow Lab Repairing Conditioner", "price_mode": "ea", "price_item": "8.99", "url": "/product/5233769_ea_000pns?name=repairing-conditioner", "cat1": "Personal Care", "cat2": "Beauty & Grooming", "cat_url": "/category/personal-care/beauty--grooming", "store_name": "PAK'nSAVE New Plymouth"}, {"product_id": "5022333-EA-000PNS", "product_name": "VO5 Firm Hold Hair Spray", "price_mode": "ea", "price_item": "6.29", "url": "/product/5022333_ea_000pns?name=firm-hold-hair-spray", "cat1": "Personal Care", "cat2": "Beauty & Grooming", "cat_url": "/category/personal-care/beauty--grooming", "store_name": "PAK'nSAVE New Plymouth"}, {"product_id": "5248968-EA-000PNS", "product_name": "Glow Lab Purple Shampoo", "price_mode": "ea", "price_item": "8.99", "url": "/product/5248968_ea_000pns?name=purple-shampoo", "cat1": "Personal Care", "cat2": "Beauty & Grooming", "cat_url": "/category/personal-care/beauty--grooming", "store_name": "PAK'nSAVE New Plymouth"}, {"product_id": "5091967-EA-000PNS", "product_name": "Pantene Pro-V 3 Minute Miracle Colour Protection Conditioner", "price_mode": "ea", "price_item": "5.99", "url": "/product/5091967_ea_000pns?name=3-minute-miracle-colour-protection-conditioner", "cat1": "Personal Care", "cat2": "Beauty & Grooming", "cat_url": "/category/personal-care/beauty--grooming", "store_name": "PAK'nSAVE New Plymouth"}, {"product_id": "5025658-EA-000PNS", "product_name": "VO5 Mega Hold Gel Spray", "price_mode": "ea", "price_item": "6.29", "url": "/product/5025658_ea_000pns?name=mega-hold-gel-spray", "cat1": "Personal Care", "cat2": "Beauty & Grooming", "cat_url": "/category/personal-care/beauty--grooming", "store_name": "PAK'nSAVE New Plymouth"}, {"product_id": "5229270-EA-000PNS", "product_name": "Schick Hydro 5 Sense Comfort Sensitive Skin Razor", "price_mode": "ea", "price_item": "15.99", "url": "/product/5229270_ea_000pns?name=hydro-5-sense-comfort-sensitive-skin-razor", "cat1": "Personal Care", "cat2": "Beauty & Grooming", "cat_url": "/category/personal-care/beauty--grooming", "store_name": "PAK'nSAVE New Plymouth"}, {"product_id": "5026248-EA-000PNS", "product_name": "Skinfood Nourish Moisturiser", "price_mode": "ea", "price_item": "9.99", "url": "/product/5026248_ea_000pns?name=nourish-moisturiser", "cat1": "Personal Care", "cat2": "Beauty & Grooming", "cat_url": "/category/personal-care/beauty--grooming", "store_name": "PAK'nSAVE New Plymouth"}, {"product_id": "5024568-EA-000PNS", "product_name": "Garnier Refreshing Make-Up Remover Wipes", "price_mode": "ea", "price_item": "7.69", "url": "/product/5024568_ea_000pns?name=refreshing-make-up-remover-wipes", "cat1": "Personal Care", "cat2": "Beauty & Grooming", "cat_url": "/category/personal-care/beauty--grooming", "store_name": "PAK'nSAVE New Plymouth"}, {"product_id": "5015404-EA-000PNS", "product_name": "Gillette Venus Comfort Glide White Tea Women's Disposable Razor + 2 Refills", "price_mode": "ea", "price_item": "13.99", "url": "/product/5015404_ea_000pns?name=comfort-glide-white-tea-women%27s-disposable-razor-%2b-2-refills", "cat1": "Personal Care", "cat2": "Beauty & Grooming", "cat_url": "/category/personal-care/beauty--grooming", "store_name": "PAK'nSAVE New Plymouth"}, {"product_id": "5252051-EA-000PNS", "product_name": "Schwarzkopf Brilliance Coffee Brown 46 Hair Colour", "price_mode": "ea", "price_item": "11.99", "url": "/product/5252051_ea_000pns?name=coffee-brown-46-hair-colour", "cat1": "Personal Care", "cat2": "Beauty & Grooming", "cat_url": "/category/personal-care/beauty--grooming", "store_name": "PAK'nSAVE New Plymouth"}, {"product_id": "5216868-EA-000PNS", "product_name": "Value Super Hold Hair Spray", "price_mode": "ea", "price_item": "6.49", "url": "/product/5216868_ea_000pns?name=super-hold-hair-spray", "cat1": "Personal Care", "cat2": "Beauty & Grooming", "cat_url": "/category/personal-care/beauty--grooming", "store_name": "PAK'nSAVE New Plymouth"}, {"product_id": "5016356-EA-000PNS", "product_name": "Cussons Talcum Powder", "price_mode": "ea", "price_item": "2.99", "url": "/product/5016356_ea_000pns?name=talcum-powder", "cat1": "Personal Care", "cat2": "Beauty & Grooming", "cat_url": "/category/personal-care/beauty--grooming", "store_name": "PAK'nSAVE New Plymouth"}, {"product_id": "5257259-EA-000PNS", "product_name": "Colgate Pro Clinical 250R Charcoal Power Toothbrush", "price_mode": "ea", "price_item": "39.99", "url": "/product/5257259_ea_000pns?name=pro-clinical-250r-charcoal-power-toothbrush", "cat1": "Personal Care", "cat2": "Beauty & Grooming", "cat_url": "/category/personal-care/beauty--grooming", "store_name": "PAK'nSAVE New Plymouth"}, {"product_id": "5245394-EA-000PNS", "product_name": "Dove Men Clinical Clean Comfort 96Hr Antiperspirant Deodorant", "price_mode": "ea", "price_item": "6.99", "url": "/product/5245394_ea_000pns?name=men-clinical-clean-comfort-96hr-antiperspirant-deodorant", "cat1": "Personal Care", "cat2": "Beauty & Grooming", "cat_url": "/category/personal-care/beauty--grooming", "store_name": "PAK'nSAVE New Plymouth"}, {"product_id": "5233702-EA-000PNS", "product_name": "Tresemme Repair & Protect 7 New Instant Recovery Mask", "price_mode": "ea", "price_item": "8.99", "url": "/product/5233702_ea_000pns?name=repair-%26-protect-7-new-instant-recovery-mask", "cat1": "Personal Care", "cat2": "Beauty & Grooming", "cat_url": "/category/personal-care/beauty--grooming", "store_name": "PAK'nSAVE New Plymouth"}, {"product_id": "5030566-EA-000PNS", "product_name": "Garnier BB Original Light Cream", "price_mode": "ea", "price_item": "15.74", "url": "/product/5030566_ea_000pns?name=bb-original-light-cream", "cat1": "Personal Care", "cat2": "Beauty & Grooming", "cat_url": "/category/personal-care/beauty--grooming", "store_name": "PAK'nSAVE New Plymouth"}, {"product_id": "5256336-EA-000PNS", "product_name": "Essano Collagen Boost Natural Skincare Pack", "price_mode": "ea", "price_item": "23.99", "url": "/product/5256336_ea_000pns?name=collagen-boost-natural-skincare-pack", "cat1": "Personal Care", "cat2": "Beauty & Grooming", "cat_url": "/category/personal-care/beauty--grooming", "store_name": "PAK'nSAVE New Plymouth"}, {"product_id": "5018022-EA-000PNS", "product_name": "Redberry Small Coloured Snagless Elastics", "price_mode": "ea", "price_item": "2.99", "url": "/product/5018022_ea_000pns?name=small-coloured-snagless-elastics", "cat1": "Personal Care", "cat2": "Beauty & Grooming", "cat_url": "/category/personal-care/beauty--grooming", "store_name": "PAK'nSAVE New Plymouth"}, {"product_id": "5005972-EA-000PNS", "product_name": "Pams Black Knees One Size 20 Denier", "price_mode": "ea", "price_item": "2.79", "url": "/product/5005972_ea_000pns?name=black-knees-one-size-20-denier", "cat1": "Personal Care", "cat2": "Beauty & Grooming", "cat_url": "/category/personal-care/beauty--grooming", "store_name": "PAK'nSAVE New Plymouth"}, {"product_id": "5019257-EA-000PNS", "product_name": "Pams Honey Opaque Trouser Socks One Size 40 Denier", "price_mode": "ea", "price_item": "2.49", "url": "/product/5019257_ea_000pns?name=honey-opaque-trouser-socks-one-size-40-denier", "cat1": "Personal Care", "cat2": "Beauty & Grooming", "cat_url": "/category/personal-care/beauty--grooming", "store_name": "PAK'nSAVE New Plymouth"}]