[{"product_id": "5026141-EA-000PNS", "product_name": "Weight Watchers Lime Jelly Crystals", "price_mode": "ea", "price_item": "1.00", "url": "/product/5026141_ea_000pns?name=lime-jelly-crystals", "cat1": "Chilled, Frozen & Desserts", "cat2": "Desserts", "cat_url": "/category/chilled-frozen-and-desserts/desserts", "store_name": "PAK'nSAVE Whakatane"}, {"product_id": "5201335-EA-000PNS", "product_name": "Much Moore Marvels Salted Chocolate Ice Cream", "price_mode": "ea", "price_item": "3.99", "url": "/product/5201335_ea_000pns?name=marvels-salted-chocolate-ice-cream", "cat1": "Chilled, Frozen & Desserts", "cat2": "Desserts", "cat_url": "/category/chilled-frozen-and-desserts/desserts", "store_name": "PAK'nSAVE Whakatane"}, {"product_id": "5026190-EA-000PNS", "product_name": "Sara Lee Homestyle Apple Pie", "price_mode": "ea", "price_item": "6.49", "url": "/product/5026190_ea_000pns?name=homestyle-apple-pie", "cat1": "Chilled, Frozen & Desserts", "cat2": "Desserts", "cat_url": "/category/chilled-frozen-and-desserts/desserts", "store_name": "PAK'nSAVE Whakatane"}, {"product_id": "5026126-EA-000PNS", "product_name": "Weight Watchers Strawberry Jelly Crystals", "price_mode": "ea", "price_item": "1.00", "url": "/product/5026126_ea_000pns?name=strawberry-jelly-crystals", "cat1": "Chilled, Frozen & Desserts", "cat2": "Desserts", "cat_url": "/category/chilled-frozen-and-desserts/desserts", "store_name": "PAK'nSAVE Whakatane"}, {"product_id": "5130524-EA-000PNS", "product_name": "Deep South Chocolate Eclair Ice Cream", "price_mode": "ea", "price_item": "4.99", "url": "/product/5130524_ea_000pns?name=chocolate-eclair-ice-cream", "cat1": "Chilled, Frozen & Desserts", "cat2": "Desserts", "cat_url": "/category/chilled-frozen-and-desserts/desserts", "store_name": "PAK'nSAVE Whakatane"}, {"product_id": "5217722-EA-000PNS", "product_name": "Value Raspberry Jelly Crystals", "price_mode": "ea", "price_item": "0.85", "url": "/product/5217722_ea_000pns?name=raspberry-jelly-crystals", "cat1": "Chilled, Frozen & Desserts", "cat2": "Desserts", "cat_url": "/category/chilled-frozen-and-desserts/desserts", "store_name": "PAK'nSAVE Whakatane"}, {"product_id": "5030917-EA-000PNS", "product_name": "Tip Top Passionfruit Ice Cream", "price_mode": "ea", "price_item": "5.99", "url": "/product/5030917_ea_000pns?name=passionfruit-ice-cream", "cat1": "Chilled, Frozen & Desserts", "cat2": "Desserts", "cat_url": "/category/chilled-frozen-and-desserts/desserts", "store_name": "PAK'nSAVE Whakatane"}, {"product_id": "5011498-EA-000PNS", "product_name": "Gregg's Golden Butterscotch Instant Desserts", "price_mode": "ea", "price_item": "1.09", "url": "/product/5011498_ea_000pns?name=golden-butterscotch-instant-desserts", "cat1": "Chilled, Frozen & Desserts", "cat2": "Desserts", "cat_url": "/category/chilled-frozen-and-desserts/desserts", "store_name": "PAK'nSAVE Whakatane"}, {"product_id": "5130542-EA-000PNS", "product_name": "Deep South Boysenberry Ripple Ice Cream", "price_mode": "ea", "price_item": "4.99", "url": "/product/5130542_ea_000pns?name=boysenberry-ripple-ice-cream", "cat1": "Chilled, Frozen & Desserts", "cat2": "Desserts", "cat_url": "/category/chilled-frozen-and-desserts/desserts", "store_name": "PAK'nSAVE Whakatane"}, {"product_id": "5130510-EA-000PNS", "product_name": "Deep South French Vanilla Ice Cream", "price_mode": "ea", "price_item": "4.99", "url": "/product/5130510_ea_000pns?name=french-vanilla-ice-cream", "cat1": "Chilled, Frozen & Desserts", "cat2": "Desserts", "cat_url": "/category/chilled-frozen-and-desserts/desserts", "store_name": "PAK'nSAVE Whakatane"}, {"product_id": "5213728-EA-000PNS", "product_name": "Deep South Mochaccino Ice Cream", "price_mode": "ea", "price_item": "4.99", "url": "/product/5213728_ea_000pns?name=mochaccino-ice-cream", "cat1": "Chilled, Frozen & Desserts", "cat2": "Desserts", "cat_url": "/category/chilled-frozen-and-desserts/desserts", "store_name": "PAK'nSAVE Whakatane"}, {"product_id": "5016701-EA-000PNS", "product_name": "Meadow Fresh Thick & Creamy Vanilla Custard", "price_mode": "ea", "price_item": "5.29", "url": "/product/5016701_ea_000pns?name=thick-%26-creamy-vanilla-custard", "cat1": "Chilled, Frozen & Desserts", "cat2": "Desserts", "cat_url": "/category/chilled-frozen-and-desserts/desserts", "store_name": "PAK'nSAVE Whakatane"}, {"product_id": "5217723-EA-000PNS", "product_name": "Value Lime Jelly Crystals", "price_mode": "ea", "price_item": "0.85", "url": "/product/5217723_ea_000pns?name=lime-jelly-crystals", "cat1": "Chilled, Frozen & Desserts", "cat2": "Desserts", "cat_url": "/category/chilled-frozen-and-desserts/desserts", "store_name": "PAK'nSAVE Whakatane"}, {"product_id": "5244922-EA-000PNS", "product_name": "Pams After Dinner Mints Dessert Bites", "price_mode": "ea", "price_item": "4.49", "url": "/product/5244922_ea_000pns?name=after-dinner-mints-dessert-bites", "cat1": "Chilled, Frozen & Desserts", "cat2": "Desserts", "cat_url": "/category/chilled-frozen-and-desserts/desserts", "store_name": "PAK'nSAVE Whakatane"}, {"product_id": "5011122-EA-000PNS", "product_name": "Kapiti Triple Choc Ice Cream", "price_mode": "ea", "price_item": "9.49", "url": "/product/5011122_ea_000pns?name=triple-choc-ice-cream", "cat1": "Chilled, Frozen & Desserts", "cat2": "Desserts", "cat_url": "/category/chilled-frozen-and-desserts/desserts", "store_name": "PAK'nSAVE Whakatane"}, {"product_id": "5011123-EA-000PNS", "product_name": "Kapiti Vanilla Bean Ice Cream", "price_mode": "ea", "price_item": "9.49", "url": "/product/5011123_ea_000pns?name=vanilla-bean-ice-cream", "cat1": "Chilled, Frozen & Desserts", "cat2": "Desserts", "cat_url": "/category/chilled-frozen-and-desserts/desserts", "store_name": "PAK'nSAVE Whakatane"}, {"product_id": "5012687-EA-000PNS", "product_name": "Meadow Fresh Custard Trio Yoghurt", "price_mode": "ea", "price_item": "3.59", "url": "/product/5012687_ea_000pns?name=custard-trio-yoghurt", "cat1": "Chilled, Frozen & Desserts", "cat2": "Desserts", "cat_url": "/category/chilled-frozen-and-desserts/desserts", "store_name": "PAK'nSAVE Whakatane"}, {"product_id": "5003974-EA-000PNS", "product_name": "Pams Chocolate Eclairs", "price_mode": "ea", "price_item": "3.79", "url": "/product/5003974_ea_000pns?name=chocolate-eclairs", "cat1": "Chilled, Frozen & Desserts", "cat2": "Desserts", "cat_url": "/category/chilled-frozen-and-desserts/desserts", "store_name": "PAK'nSAVE Whakatane"}, {"product_id": "5031606-EA-000PNS", "product_name": "Much Moore Marvels Salted Caramel Ice Cream", "price_mode": "ea", "price_item": "3.99", "url": "/product/5031606_ea_000pns?name=marvels-salted-caramel-ice-cream", "cat1": "Chilled, Frozen & Desserts", "cat2": "Desserts", "cat_url": "/category/chilled-frozen-and-desserts/desserts", "store_name": "PAK'nSAVE Whakatane"}, {"product_id": "5093679-EA-000PNS", "product_name": "Pams Passionfruit Cheesecake", "price_mode": "ea", "price_item": "5.59", "url": "/product/5093679_ea_000pns?name=passionfruit-cheesecake", "cat1": "Chilled, Frozen & Desserts", "cat2": "Desserts", "cat_url": "/category/chilled-frozen-and-desserts/desserts", "store_name": "PAK'nSAVE Whakatane"}]