[{"product_id": "5225014-EA-000PNS", "product_name": "Value Multi-Purpose Cleaning Cloths", "price_mode": "ea", "price_item": "5.19", "url": "/product/5225014_ea_000pns?name=multi-purpose-cleaning-cloths", "cat1": "Kitchen, Dining & Household", "cat2": "Cleaning Products", "cat_url": "/category/kitchen-dining-and-household/cleaning-products", "store_name": "PAK'nSAVE Tamatea"}, {"product_id": "5242815-EA-000PNS", "product_name": "Earthwise Lemon & Aloe Vera Plant Powered Dish Liquid", "price_mode": "ea", "price_item": "3.49", "url": "/product/5242815_ea_000pns?name=lemon-%26-aloe-vera-plant-powered-dish-liquid", "cat1": "Kitchen, Dining & Household", "cat2": "Cleaning Products", "cat_url": "/category/kitchen-dining-and-household/cleaning-products", "store_name": "PAK'nSAVE Tamatea"}, {"product_id": "5239674-EA-000PNS", "product_name": "Mr Muscle Fresh Linen All Purpose Cleaner", "price_mode": "ea", "price_item": "2.99", "url": "/product/5239674_ea_000pns?name=fresh-linen-all-purpose-cleaner", "cat1": "Kitchen, Dining & Household", "cat2": "Cleaning Products", "cat_url": "/category/kitchen-dining-and-household/cleaning-products", "store_name": "PAK'nSAVE Tamatea"}, {"product_id": "5016027-EA-000PNS", "product_name": "Dettol Lavender Disinfectant Liquid", "price_mode": "ea", "price_item": "2.79", "url": "/product/5016027_ea_000pns?name=lavender-disinfectant-liquid", "cat1": "Kitchen, Dining & Household", "cat2": "Cleaning Products", "cat_url": "/category/kitchen-dining-and-household/cleaning-products", "store_name": "PAK'nSAVE Tamatea"}, {"product_id": "5236809-EA-000PNS", "product_name": "Duck Tropical Sunshine Fresh Discs", "price_mode": "ea", "price_item": "3.99", "url": "/product/5236809_ea_000pns?name=tropical-sunshine-fresh-discs", "cat1": "Kitchen, Dining & Household", "cat2": "Cleaning Products", "cat_url": "/category/kitchen-dining-and-household/cleaning-products", "store_name": "PAK'nSAVE Tamatea"}, {"product_id": "5001174-EA-000PNS", "product_name": "Jif Cloths", "price_mode": "ea", "price_item": "3.09", "url": "/product/5001174_ea_000pns?name=cloths", "cat1": "Kitchen, Dining & Household", "cat2": "Cleaning Products", "cat_url": "/category/kitchen-dining-and-household/cleaning-products", "store_name": "PAK'nSAVE Tamatea"}, {"product_id": "5242589-EA-000PNS", "product_name": "Best Cellulose Sponge Scourer", "price_mode": "ea", "price_item": "2.99", "url": "/product/5242589_ea_000pns?name=cellulose-sponge-scourer", "cat1": "Kitchen, Dining & Household", "cat2": "Cleaning Products", "cat_url": "/category/kitchen-dining-and-household/cleaning-products", "store_name": "PAK'nSAVE Tamatea"}, {"product_id": "5016411-EA-000PNS", "product_name": "Active Regular Rinse Aid", "price_mode": "ea", "price_item": "4.99", "url": "/product/5016411_ea_000pns?name=regular-rinse-aid", "cat1": "Kitchen, Dining & Household", "cat2": "Cleaning Products", "cat_url": "/category/kitchen-dining-and-household/cleaning-products", "store_name": "PAK'nSAVE Tamatea"}, {"product_id": "5255451-EA-000PNS", "product_name": "Duck Spring Flowers Extra Power Toilet Shield", "price_mode": "ea", "price_item": "3.09", "url": "/product/5255451_ea_000pns?name=spring-flowers-extra-power-toilet-shield", "cat1": "Kitchen, Dining & Household", "cat2": "Cleaning Products", "cat_url": "/category/kitchen-dining-and-household/cleaning-products", "store_name": "PAK'nSAVE Tamatea"}, {"product_id": "5213495-EA-000PNS", "product_name": "Bref Blue Active Chlorine", "price_mode": "ea", "price_item": "2.49", "url": "/product/5213495_ea_000pns?name=blue-active-chlorine", "cat1": "Kitchen, Dining & Household", "cat2": "Cleaning Products", "cat_url": "/category/kitchen-dining-and-household/cleaning-products", "store_name": "PAK'nSAVE Tamatea"}, {"product_id": "5016649-EA-000PNS", "product_name": "Earthwise Lemon Dishwasher Powder", "price_mode": "ea", "price_item": "5.99", "url": "/product/5016649_ea_000pns?name=lemon-dishwasher-powder", "cat1": "Kitchen, Dining & Household", "cat2": "Cleaning Products", "cat_url": "/category/kitchen-dining-and-household/cleaning-products", "store_name": "PAK'nSAVE Tamatea"}, {"product_id": "5211408-EA-000PNS", "product_name": "Dettol Lemon Cleaning Wipes", "price_mode": "ea", "price_item": "3.99", "url": "/product/5211408_ea_000pns?name=lemon-cleaning-wipes", "cat1": "Kitchen, Dining & Household", "cat2": "Cleaning Products", "cat_url": "/category/kitchen-dining-and-household/cleaning-products", "store_name": "PAK'nSAVE Tamatea"}, {"product_id": "5025518-EA-000PNS", "product_name": "Active Regular Rinse Aid", "price_mode": "ea", "price_item": "2.99", "url": "/product/5025518_ea_000pns?name=regular-rinse-aid", "cat1": "Kitchen, Dining & Household", "cat2": "Cleaning Products", "cat_url": "/category/kitchen-dining-and-household/cleaning-products", "store_name": "PAK'nSAVE Tamatea"}, {"product_id": "5023961-EA-000PNS", "product_name": "Down To Earth Dishwash Liquid Refill", "price_mode": "ea", "price_item": "2.09", "url": "/product/5023961_ea_000pns?name=dishwash-liquid-refill", "cat1": "Kitchen, Dining & Household", "cat2": "Cleaning Products", "cat_url": "/category/kitchen-dining-and-household/cleaning-products", "store_name": "PAK'nSAVE Tamatea"}, {"product_id": "5250074-EA-000PNS", "product_name": "Duck Marine Foaming Bleach Gel", "price_mode": "ea", "price_item": "3.49", "url": "/product/5250074_ea_000pns?name=marine-foaming-bleach-gel", "cat1": "Kitchen, Dining & Household", "cat2": "Cleaning Products", "cat_url": "/category/kitchen-dining-and-household/cleaning-products", "store_name": "PAK'nSAVE Tamatea"}, {"product_id": "5015721-EA-000PNS", "product_name": "Mr Muscle Crystal Rain Glass Cleaner", "price_mode": "ea", "price_item": "2.99", "url": "/product/5015721_ea_000pns?name=crystal-rain-glass-cleaner", "cat1": "Kitchen, Dining & Household", "cat2": "Cleaning Products", "cat_url": "/category/kitchen-dining-and-household/cleaning-products", "store_name": "PAK'nSAVE Tamatea"}, {"product_id": "5030197-EA-000PNS", "product_name": "Chux Heavy Duty Superwipes On A Roll", "price_mode": "ea", "price_item": "7.29", "url": "/product/5030197_ea_000pns?name=heavy-duty-superwipes-on-a-roll", "cat1": "Kitchen, Dining & Household", "cat2": "Cleaning Products", "cat_url": "/category/kitchen-dining-and-household/cleaning-products", "store_name": "PAK'nSAVE Tamatea"}, {"product_id": "5002850-EA-000PNS", "product_name": "Chux Giant Superwipes Cleaning Cloth", "price_mode": "ea", "price_item": "4.65", "url": "/product/5002850_ea_000pns?name=giant-superwipes-cleaning-cloth", "cat1": "Kitchen, Dining & Household", "cat2": "Cleaning Products", "cat_url": "/category/kitchen-dining-and-household/cleaning-products", "store_name": "PAK'nSAVE Tamatea"}, {"product_id": "5249619-EA-000PNS", "product_name": "Duck Citrus Deep Action Gel", "price_mode": "ea", "price_item": "3.29", "url": "/product/5249619_ea_000pns?name=citrus-deep-action-gel", "cat1": "Kitchen, Dining & Household", "cat2": "Cleaning Products", "cat_url": "/category/kitchen-dining-and-household/cleaning-products", "store_name": "PAK'nSAVE Tamatea"}, {"product_id": "5006837-EA-000PNS", "product_name": "Active Lemon Automatic Dishwashing Powder", "price_mode": "ea", "price_item": "4.99", "url": "/product/5006837_ea_000pns?name=lemon-automatic-dishwashing-powder", "cat1": "Kitchen, Dining & Household", "cat2": "Cleaning Products", "cat_url": "/category/kitchen-dining-and-household/cleaning-products", "store_name": "PAK'nSAVE Tamatea"}]