[{"product_id": "5267728-EA-000PNS", "product_name": "Manly Park Kitchen Vegetairan Tagine Meal", "price_mode": "ea", "price_item": "10.99", "url": "/product/5267728_ea_000pns?name=vegetairan-tagine-meal", "cat1": "Fresh Foods & Bakery", "cat2": "Deli, Salads & Cooked Meats", "cat_url": "/category/fresh-foods-and-bakery/deli-salads--cooked-meats", "store_name": "PAK'nSAVE Sylvia Park"}, {"product_id": "5265838-EA-000PNS", "product_name": "Scalini's At Home Ready Meal Scaloppine Marsala", "price_mode": "ea", "price_item": "18.99", "url": "/product/5265838_ea_000pns?name=at-home-ready-meal-scaloppine-marsala", "cat1": "Fresh Foods & Bakery", "cat2": "Deli, Salads & Cooked Meats", "cat_url": "/category/fresh-foods-and-bakery/deli-salads--cooked-meats", "store_name": "PAK'nSAVE Sylvia Park"}, {"product_id": "5210623-EA-000PNS", "product_name": "Deroni Vegetable Brushetta", "price_mode": "ea", "price_item": "6.49", "url": "/product/5210623_ea_000pns?name=vegetable-brushetta", "cat1": "Fresh Foods & Bakery", "cat2": "Deli, Salads & Cooked Meats", "cat_url": "/category/fresh-foods-and-bakery/deli-salads--cooked-meats", "store_name": "PAK'nSAVE Sylvia Park"}, {"product_id": "5030910-EA-000PNS", "product_name": "Service Deli Pronto e Fresco", "price_mode": "ea", "price_item": "27.90", "url": "/product/5030910_ea_000pns?name=pronto-e-fresco", "cat1": "Fresh Foods & Bakery", "cat2": "Deli, Salads & Cooked Meats", "cat_url": "/category/fresh-foods-and-bakery/deli-salads--cooked-meats", "store_name": "PAK'nSAVE Sylvia Park"}, {"product_id": "5111808-KGM-000PNS", "product_name": "Unbranded THAI BEEF NOODLE SALAD", "price_mode": "kg", "price_item": "32.90", "url": "/product/5111808_kgm_000pns?name=thai-beef-noodle-salad", "cat1": "Fresh Foods & Bakery", "cat2": "Deli, Salads & Cooked Meats", "cat_url": "/category/fresh-foods-and-bakery/deli-salads--cooked-meats", "store_name": "PAK'nSAVE Sylvia Park"}, {"product_id": "5006418-EA-000PNS", "product_name": "Service Deli Potato Gnocchi Tomato", "price_mode": "ea", "price_item": "4.79", "url": "/product/5006418_ea_000pns?name=potato-gnocchi-tomato", "cat1": "Fresh Foods & Bakery", "cat2": "Deli, Salads & Cooked Meats", "cat_url": "/category/fresh-foods-and-bakery/deli-salads--cooked-meats", "store_name": "PAK'nSAVE Sylvia Park"}]